hhui_mcp/__init__.py
hhui_mcp-0.1.0.dist-info/WHEEL
hhui_mcp-0.1.0.dist-info/entry_points.txt
hhui_mcp-0.1.0.dist-info/METADATA
hhui_mcp-0.1.0.dist-info/RECORD
