Metadata-Version: 2.3
Name: hhui-mcp
Version: 0.1.0
Summary: Add your description here
Author: 只爱划船.
Author-email: 只爱划船. <hhui000927@gmail.com>
Requires-Dist: mcp[cli]>=1.26.0
Requires-Python: >=3.13
